poetry_env_test/__init__.py
poetry_env_test/backup_dependencies.py
poetry_env_test/check_project_setup.py
poetry_env_test/clean_project_setup.py
poetry_env_test/utils/__init__.py
poetry_env_test/utils/utils.py
poetry_env_test-0.1.2.dist-info/METADATA
poetry_env_test-0.1.2.dist-info/WHEEL
poetry_env_test-0.1.2.dist-info/entry_points.txt
poetry_env_test-0.1.2.dist-info/RECORD
