Metadata-Version: 2.1
Name: poetry-env-test
Version: 0.1.2
Summary: A package to manage and verify Python project environments using Poetry.
License: MIT
Author: Your Name
Author-email: your.email@example.com
Requires-Python: >=3.10,<4.0
Classifier: License :: OSI Approved :: MIT License
Classifier: Programming Language :: Python :: 3
Classifier: Programming Language :: Python :: 3.10
Classifier: Programming Language :: Python :: 3.11
Classifier: Programming Language :: Python :: 3.12
